<Properties StartupConfiguration="{DF6900A8-62F7-4915-A4C0-040D23869EA0}|Default">
  <MultiItemStartupConfigurations />
  <MonoDevelop.Ide.DebuggingService.Breakpoints>
    <BreakpointStore />
  </MonoDevelop.Ide.DebuggingService.Breakpoints>
  <MonoDevelop.Ide.Workbench ActiveDocument="Teacher.cs">
    <Files>
      <File FileName="Program.cs" Line="19" Column="1" />
      <File FileName="Student.cs" Line="23" Column="1" />
      <File FileName="Teacher.cs" Line="22" Column="1" />
    </Files>
    <Pads>
      <Pad Id="ProjectPad">
        <State name="__root__">
          <Node name="TeacherAndStudent" expanded="True">
            <Node name="TeacherAndStudent" expanded="True">
              <Node name="Teacher.cs" selected="True" />
            </Node>
          </Node>
        </State>
      </Pad>
      <Pad Id="MonoDevelop.Debugger.WatchPad">
        <State />
      </Pad>
    </Pads>
  </MonoDevelop.Ide.Workbench>
  <MonoDevelop.Ide.DebuggingService.PinnedWatches />
  <MonoDevelop.Ide.Workspace ActiveConfiguration="Debug" />
  <MonoDevelop.Ide.ItemProperties.TeacherAndStudent PreferredExecutionTarget="MonoDevelop.Default" />
</Properties>