<Properties StartupConfiguration="{5A9B2A4F-0BF2-4913-8B9E-20CB45FA4E0F}|Default">
  <MultiItemStartupConfigurations />
  <MonoDevelop.Ide.ItemProperties.PersonalFinance PreferredExecutionTarget="MonoDevelop.Default" FirstBuild="True" />
  <MonoDevelop.Ide.Workbench ActiveDocument="Program.cs">
    <Files>
      <File FileName="Program.cs" Line="32" Column="1" />
    </Files>
    <Pads>
      <Pad Id="ProjectPad">
        <State name="__root__">
          <Node name="PersonalFinance" expanded="True">
            <Node name="PersonalFinance" expanded="True" />
          </Node>
        </State>
      </Pad>
      <Pad Id="MonoDevelop.Debugger.WatchPad">
        <State />
      </Pad>
    </Pads>
  </MonoDevelop.Ide.Workbench>
  <MonoDevelop.Ide.DebuggingService.Breakpoints>
    <BreakpointStore />
  </MonoDevelop.Ide.DebuggingService.Breakpoints>
  <MonoDevelop.Ide.DebuggingService.PinnedWatches />
  <MonoDevelop.Ide.Workspace ActiveConfiguration="Debug" />
</Properties>